librespyte/__init__.py
librespyte/_version.py
librespyte/history.py
librespyte/pager.py
librespyte/rest.py
respyte-1.0.5.data/scripts/respyte
respyte-1.0.5.dist-info/METADATA
respyte-1.0.5.dist-info/WHEEL
respyte-1.0.5.dist-info/top_level.txt
respyte-1.0.5.dist-info/RECORD
