Metadata-Version: 2.1
Name: respyte
Version: 1.0.5
Summary: respyte tui
Home-page: https://github.com/ginsburgnm/respyte
Author: Noah Ginsburg
Author-email: ginsburgnm@gmail.com
License: GPLV3
Platform: UNKNOWN
Classifier: Environment :: Console
Classifier: Intended Audience :: Developers
Classifier: Intended Audience :: Information Technology
Classifier: Intended Audience :: System Administrators
Classifier: License :: OSI Approved :: GNU General Public License v3 (GPLv3)
Classifier: Operating System :: OS Independent
Classifier: Programming Language :: Python :: 3.5
Classifier: Programming Language :: Python :: 3.6
Classifier: Programming Language :: Python :: 3.7
Classifier: Programming Language :: Python :: 3.8
Requires-Dist: asciimatics (>=1.11.0)
Requires-Dist: PyYAML (>=5.4)
Requires-Dist: requests (>=2.22.0)
Requires-Dist: ConfigArgParse (>-1.0)
Provides-Extra: testing
Requires-Dist: mock ; extra == 'testing'
Requires-Dist: tox ; extra == 'testing'
